version_differ/__init__.py
version_differ/__main__.py
version_differ/common.py
version_differ/download.py
version_differ/py.typed
version_differ/version_differ.py
version_differ-0.3.15.dist-info/entry_points.txt
version_differ-0.3.15.dist-info/LICENSE
version_differ-0.3.15.dist-info/WHEEL
version_differ-0.3.15.dist-info/METADATA
version_differ-0.3.15.dist-info/RECORD
