Metadata-Version: 2.1
Name: version-differ
Version: 0.3.15
Summary: Accurate diffing between two versions of a project
Home-page: https://github.com/nasifimtiazohi/version-differ
License: MIT
Author: Nasif Imtiaz
Author-email: nasifimtiaz88@gmail.com
Requires-Python: >=3.7.1,<4.0.0
Classifier: License :: OSI Approved :: MIT License
Classifier: Programming Language :: Python :: 3
Classifier: Programming Language :: Python :: 3.10
Classifier: Programming Language :: Python :: 3.6
Classifier: Programming Language :: Python :: 3.7
Classifier: Programming Language :: Python :: 3.8
Classifier: Programming Language :: Python :: 3.9
Requires-Dist: GitPython (>=3.1.24,<4.0.0)
Requires-Dist: PyYAML (>=5.4.1,<6.0.0)
Requires-Dist: click (>=8.0.0,<9.0.0)
Requires-Dist: pygit2 (>=1.7.2,<2.0.0)
Requires-Dist: requests (>=2.26.0,<3.0.0)
Requires-Dist: rich (>=10.3.0,<11.0.0)
Requires-Dist: unidiff (>=0.7.0,<0.8.0)
Requires-Dist: urllib3 (>=1.26.7,<2.0.0)
Project-URL: Documentation, https://version-differ.readthedocs.io
Project-URL: Repository, https://github.com/nasifimtiazohi/version-differ
